simple_oauth_server/__init__.py
simple_oauth_server/asymmetric_key_pair.py
simple_oauth_server/authorize_api_spec.yaml
simple_oauth_server/jwks_api_spec.yaml
simple_oauth_server/jwks_handler.py
simple_oauth_server/token_authorizer.py
simple_oauth_server/token_decoder.py
simple_oauth_server/token_validator.py
simple_oauth_server/validate_api_spec.yaml
simple_oauth_server-0.1.5.dist-info/METADATA
simple_oauth_server-0.1.5.dist-info/WHEEL
simple_oauth_server-0.1.5.dist-info/licenses/LICENSE
simple_oauth_server-0.1.5.dist-info/RECORD
